odoo/addons/account_group_menu/README.rst
odoo/addons/account_group_menu/__init__.py
odoo/addons/account_group_menu/__manifest__.py
odoo/addons/account_group_menu/demo/account_group.xml
odoo/addons/account_group_menu/demo/account_tax_group.xml
odoo/addons/account_group_menu/models/__init__.py
odoo/addons/account_group_menu/models/account_group.py
odoo/addons/account_group_menu/models/account_tax_group.py
odoo/addons/account_group_menu/views/account_group.xml
odoo/addons/account_group_menu/views/account_tax_group.xml
odoo11_addon_account_group_menu-11.0.1.0.0.dist-info/DESCRIPTION.rst
odoo11_addon_account_group_menu-11.0.1.0.0.dist-info/METADATA
odoo11_addon_account_group_menu-11.0.1.0.0.dist-info/RECORD
odoo11_addon_account_group_menu-11.0.1.0.0.dist-info/WHEEL
odoo11_addon_account_group_menu-11.0.1.0.0.dist-info/metadata.json
odoo11_addon_account_group_menu-11.0.1.0.0.dist-info/top_level.txt
